[{"name":"Zamazenta V #212","price":14.76,"url":"https://www.pricecharting.com/game/pokemon-sword-\u0026-shield/zamazenta-v-212","picture":"https://storage.googleapis.com/images.pricecharting.com/9cbd17776f8437c7e590216008ea790e3877fd3a7826b18fdf825cf3a3337ac5/240.jpg","id":19083},{"name":"Snorlax VMax #206","price":39.42,"url":"https://www.pricecharting.com/game/pokemon-sword-\u0026-shield/snorlax-vmax-206","picture":"https://storage.googleapis.com/images.pricecharting.com/7ed2b00c936682a8cdf41d383dbfd81599957108b42696b10fdcb183378987d1/240.jpg","id":19086},{"name":"Ultra Premium Collection [Charizard] Box","price":178.0,"url":"https://www.pricecharting.com/game/pokemon-sword-\u0026-shield/ultra-premium-collection-charizard-box","picture":"https://storage.googleapis.com/images.pricecharting.com/61a6ce44794b83e3bc7916b0ee798f7443463da2e5c520f30336ea581de100e4/240.jpg","id":19090},{"name":"Lapras Vmax #50","price":4.22,"url":"https://www.pricecharting.com/game/pokemon-sword-\u0026-shield/lapras-vmax-50","picture":"https://storage.googleapis.com/images.pricecharting.com/da054de4d0d7920f5292c273d7e786148f0d4780f53018955c3c209706555086/240.jpg","id":19091},{"name":"Marnie #200","price":28.29,"url":"https://www.pricecharting.com/game/pokemon-sword-\u0026-shield/marnie-200","picture":"https://storage.googleapis.com/images.pricecharting.com/e19cd1fde6f6de0e76cceffde1353cb805d6a8e6ee39ca8413e3d92b045cb9a1/240.jpg","id":19094},{"name":"Zacian V #138","price":2.48,"url":"https://www.pricecharting.com/game/pokemon-sword-\u0026-shield/zacian-v-138","picture":"https://storage.googleapis.com/images.pricecharting.com/a65cd0feeb38669638d10946e82a3accacda41e4e1b3d38bfccf7ec65818a79b/240.jpg","id":19095},{"name":"Snorlax Vmax #142","price":16.8,"url":"https://www.pricecharting.com/game/pokemon-sword-\u0026-shield/snorlax-vmax-142","picture":"https://storage.googleapis.com/images.pricecharting.com/e5f3d1f79dea700a66d4c82c390767301be658f70be6c684b0b6c868f4ed6ac1/240.jpg","id":19097},{"name":"Lapras VMax #203","price":11.77,"url":"https://www.pricecharting.com/game/pokemon-sword-\u0026-shield/lapras-vmax-203","picture":"https://storage.googleapis.com/images.pricecharting.com/7026763c7df47e8061daf645f7843381029d311fb896157f25a1713962bfac11/240.jpg","id":19103},{"name":"Snorlax #140","price":2.2,"url":"https://www.pricecharting.com/game/pokemon-sword-\u0026-shield/snorlax-140","picture":"https://storage.googleapis.com/images.pricecharting.com/487da558e87de5c647bbea8b105b110a7f7c648711de813a8410de35d12beb34/240.jpg","id":19105},{"name":"Marnie #208","price":15.45,"url":"https://www.pricecharting.com/game/pokemon-sword-\u0026-shield/marnie-208","picture":"https://storage.googleapis.com/images.pricecharting.com/c4be8d27a328369a65df4b7aee0ea64c83fe099b552d58f51b092f719e23d069/240.jpg","id":19116},{"name":"Zacian V #211","price":14.61,"url":"https://www.pricecharting.com/game/pokemon-sword-\u0026-shield/zacian-v-211","picture":"https://storage.googleapis.com/images.pricecharting.com/13b0b429b6324ac42b19d77a07334a711a2373816a398c95907b3495985dc872/240.jpg","id":19124},{"name":"Victini V #25","price":2.24,"url":"https://www.pricecharting.com/game/pokemon-sword-\u0026-shield/victini-v-25","picture":"https://storage.googleapis.com/images.pricecharting.com/cb13da32da375a2162cb972529bb20db4582eb715a9777bd35edb6d28831d80c/240.jpg","id":19127},{"name":"Snorlax V #197","price":12.3,"url":"https://www.pricecharting.com/game/pokemon-sword-\u0026-shield/snorlax-v-197","picture":"https://storage.googleapis.com/images.pricecharting.com/5293b1ce3155888c2b512579d9c0a4523a523347086e91eaddeecb02e95a1034/240.jpg","id":19132},{"name":"Morpeko Vmax #80","price":2.75,"url":"https://www.pricecharting.com/game/pokemon-sword-\u0026-shield/morpeko-vmax-80","picture":"https://storage.googleapis.com/images.pricecharting.com/5e1aafc6a068ccefe97cf49ff77144e9cfbecd1324413b9e58c352f37f5feb01/240.jpg","id":19133},{"name":"Stonjourner Vmax #116","price":2.47,"url":"https://www.pricecharting.com/game/pokemon-sword-\u0026-shield/stonjourner-vmax-116","picture":"https://storage.googleapis.com/images.pricecharting.com/23e1a21c3099018e2cc45a86fbc11980a571032f9cf6b1f846f1d2060c225304/240.jpg","id":19136},{"name":"Zamazenta V #139","price":2.37,"url":"https://www.pricecharting.com/game/pokemon-sword-\u0026-shield/zamazenta-v-139","picture":"https://storage.googleapis.com/images.pricecharting.com/748d2bfbccd7c4c28f12d38192e0e7f8a6d77b8e1ef02bee2dc320cbb7066f04/240.jpg","id":19137},{"name":"Snorlax V #141","price":4.57,"url":"https://www.pricecharting.com/game/pokemon-sword-\u0026-shield/snorlax-v-141","picture":"https://storage.googleapis.com/images.pricecharting.com/bfaf27e53739803feb66335385d9858c2d20978b8c37a116c5231aeef8455b3c/240.jpg","id":19138},{"name":"Celebi V #1","price":2.99,"url":"https://www.pricecharting.com/game/pokemon-sword-\u0026-shield/celebi-v-1","picture":"https://storage.googleapis.com/images.pricecharting.com/92aac2e2c75087f8777b045760426b44403d6ce02b520af40562d9f0a36bae2b/240.jpg","id":19142},{"name":"Lapras V #49","price":3.04,"url":"https://www.pricecharting.com/game/pokemon-sword-\u0026-shield/lapras-v-49","picture":"https://storage.googleapis.com/images.pricecharting.com/faa2a7e600e9735bd03e8a9c063d7adc690f1d9a224af30ea8b87f7185095d34/240.jpg","id":19150},{"name":"Keldeo V #53","price":2.24,"url":"https://www.pricecharting.com/game/pokemon-sword-\u0026-shield/keldeo-v-53","picture":"https://storage.googleapis.com/images.pricecharting.com/d7b074da64bd6ffdbd98410a42b2c90dbe3386a4abc7bafd095a37f43a3e90b1/240.jpg","id":19157},{"name":"Morpeko VMax #204","price":7.85,"url":"https://www.pricecharting.com/game/pokemon-sword-\u0026-shield/morpeko-vmax-204","picture":"https://storage.googleapis.com/images.pricecharting.com/d352e1716b3c7fd6fe68d7adae027f038ecbca3a702deb9c0eecc672867a3c3c/240.jpg","id":19160},{"name":"Regirock V #104","price":1.99,"url":"https://www.pricecharting.com/game/pokemon-sword-\u0026-shield/regirock-v-104","picture":"https://storage.googleapis.com/images.pricecharting.com/0289e833ec38f1c552405c7b5c5f9439fc791c272f93e323d68324d997d9e56f/240.jpg","id":19161},{"name":"Lucario VStar [Jumbo] #SWSH214","price":3.14,"url":"https://www.pricecharting.com/game/pokemon-sword-\u0026-shield/lucario-vstar-jumbo-swsh214","picture":"https://storage.googleapis.com/images.pricecharting.com/eqpiva5nzf7knzzn/240.jpg","id":19169},{"name":"Snorlax [Cosmos Holo] #140","price":2.77,"url":"https://www.pricecharting.com/game/pokemon-sword-\u0026-shield/snorlax-cosmos-holo-140","picture":"https://storage.googleapis.com/images.pricecharting.com/391341a0ca1b0486a61a64a44389b8ef2f57728b001faa0af36725d75f2f1d27/240.jpg","id":19174},{"name":"Stonjourner VMax #205","price":6.0,"url":"https://www.pricecharting.com/game/pokemon-sword-\u0026-shield/stonjourner-vmax-205","picture":"https://storage.googleapis.com/images.pricecharting.com/27eec6eec6f40791be0ca7d7acbc8fd064d7dbceb81e21fd4c134bc6ceae06eb/240.jpg","id":19180},{"name":"Pikachu #65","price":1.5,"url":"https://www.pricecharting.com/game/pokemon-sword-\u0026-shield/pikachu-65","picture":"https://storage.googleapis.com/images.pricecharting.com/3d40ad9c47286adf0b46efc7049298f419b3b8438383a9bbb41b4fb6207d9f2f/240.jpg","id":19181},{"name":"Professor\u0027s Research #209","price":5.18,"url":"https://www.pricecharting.com/game/pokemon-sword-\u0026-shield/professor%27s-research-209","picture":"https://storage.googleapis.com/images.pricecharting.com/b6d627b81e668eaa27ff0579c372156d2b11bb4da1ec73e593783c7330e26d6b/240.jpg","id":19186},{"name":"Morpeko V #79","price":2.09,"url":"https://www.pricecharting.com/game/pokemon-sword-\u0026-shield/morpeko-v-79","picture":"https://storage.googleapis.com/images.pricecharting.com/017a2dc5c9ff110c33288f32d1ac75cd95f231b995695c918db32d781a4ee665/240.jpg","id":19188},{"name":"Dhelmise V #9","price":1.8,"url":"https://www.pricecharting.com/game/pokemon-sword-\u0026-shield/dhelmise-v-9","picture":"https://storage.googleapis.com/images.pricecharting.com/83a031bb2d56c1013e9c0c25c500545e248c79ba87fa153bb0aeb82a290171c6/240.jpg","id":19190},{"name":"Booster Box [Base Set]","price":332.58,"url":"https://www.pricecharting.com/game/pokemon-sword-\u0026-shield/booster-box-base-set","picture":"https://storage.googleapis.com/images.pricecharting.com/baf59ecdf4dee6d9996c7e69ad0fc24b0af27c4f01285e0f4e034a544815d7d8/240.jpg","id":19198},{"name":"Zamazenta V #196","price":5.26,"url":"https://www.pricecharting.com/game/pokemon-sword-\u0026-shield/zamazenta-v-196","picture":"https://storage.googleapis.com/images.pricecharting.com/6f572295a5274951205388eed3786d7af3b07c56bd17f259628f035724e28c3d/240.jpg","id":19201},{"name":"Tapu Koko V #72","price":2.06,"url":"https://www.pricecharting.com/game/pokemon-sword-\u0026-shield/tapu-koko-v-72","picture":"https://storage.googleapis.com/images.pricecharting.com/14786b6280c9b7214ab55887053c11261b446e6e8ba029f2d4157fa19d5213d5/240.jpg","id":19208},{"name":"Zacian V #195","price":5.19,"url":"https://www.pricecharting.com/game/pokemon-sword-\u0026-shield/zacian-v-195","picture":"https://storage.googleapis.com/images.pricecharting.com/681ae894046a9fdd666aa28ec790943920f63d25aadc73612db7abaea55d01b5/240.jpg","id":19216},{"name":"Cramorant V #155","price":1.85,"url":"https://www.pricecharting.com/game/pokemon-sword-\u0026-shield/cramorant-v-155","picture":"https://storage.googleapis.com/images.pricecharting.com/c6f6aaf0833117181eda3284d21b5c86a2a273235a6e0e89da442fd3c9d84b7b/240.jpg","id":19218},{"name":"Lapras V #189","price":4.8,"url":"https://www.pricecharting.com/game/pokemon-sword-\u0026-shield/lapras-v-189","picture":"https://storage.googleapis.com/images.pricecharting.com/255c8e4907d8d27c5b3b08962b40e6b16e5d039d0795d412e6902cc117d48b3d/240.jpg","id":19221},{"name":"Gengar [Holo] #85","price":3.68,"url":"https://www.pricecharting.com/game/pokemon-sword-\u0026-shield/gengar-holo-85","picture":"https://storage.googleapis.com/images.pricecharting.com/a0e83a8c345e7465ba982341b997dc6338c3fb2a96b4790b50b4a78929375599/240.jpg","id":19222},{"name":"Wobbuffet V #86","price":1.97,"url":"https://www.pricecharting.com/game/pokemon-sword-\u0026-shield/wobbuffet-v-86","picture":"https://storage.googleapis.com/images.pricecharting.com/9fda121d4725408befac77fd98cd414feb409479661e8fbeb029c0783ac04f83/240.jpg","id":19238},{"name":"Electric Energy","price":0.79,"url":"https://www.pricecharting.com/game/pokemon-sword-\u0026-shield/electric-energy","picture":"https://storage.googleapis.com/images.pricecharting.com/ad079498dede152dc7f7c1660a2e1d846f058a8a2f6e9fc6fecf6f89eaf13290/240.jpg","id":19240},{"name":"Indeedee V #91","price":1.79,"url":"https://www.pricecharting.com/game/pokemon-sword-\u0026-shield/indeedee-v-91","picture":"https://storage.googleapis.com/images.pricecharting.com/47d291ff766bec289e1cd9d97909e2867a05cee233815840cbc6b50afd71ed48/240.jpg","id":19243},{"name":"Quick Ball #216","price":9.99,"url":"https://www.pricecharting.com/game/pokemon-sword-\u0026-shield/quick-ball-216","picture":"https://storage.googleapis.com/images.pricecharting.com/323151a0122bdf84e2d941786d310cbb289f27ed7b37b4c4a35876b4694f487e/240.jpg","id":19244},{"name":"Bede #207","price":5.96,"url":"https://www.pricecharting.com/game/pokemon-sword-\u0026-shield/bede-207","picture":"https://storage.googleapis.com/images.pricecharting.com/bd1bb2d2f1e1b985d788faf807ea46e7fba1b8b3caa0df16e5f5e37b3b82d30c/240.jpg","id":19258},{"name":"Sableye V #120","price":2.49,"url":"https://www.pricecharting.com/game/pokemon-sword-\u0026-shield/sableye-v-120","picture":"https://storage.googleapis.com/images.pricecharting.com/80807ebc66746755a7c1d5f40eda59b15e56a05e03d6421058bdc1b697b6f56e/240.jpg","id":19261},{"name":"Cinderace #34","price":1.3,"url":"https://www.pricecharting.com/game/pokemon-sword-\u0026-shield/cinderace-34","picture":"https://storage.googleapis.com/images.pricecharting.com/a7b7ac0135ec8070aefa0060653bfc76e1b34a62b82687a63b2301332c8b5b9f/240.jpg","id":19263},{"name":"Booster Pack [Base Set]","price":5.12,"url":"https://www.pricecharting.com/game/pokemon-sword-\u0026-shield/booster-pack-base-set","picture":"https://storage.googleapis.com/images.pricecharting.com/24acfb504402769db2144233c1081f8e6f11757f794c1995b8ba6e1a36c29e07/240.jpg","id":19267},{"name":"Boltund #76","price":2.09,"url":"https://www.pricecharting.com/game/pokemon-sword-\u0026-shield/boltund-76","picture":"https://storage.googleapis.com/images.pricecharting.com/7f67332e9dfa88d7d00e77d59c5720cfd97dffbc1f7f794a6f084d0cb2bd1de4/240.jpg","id":19275},{"name":"Torkoal V #24","price":2.07,"url":"https://www.pricecharting.com/game/pokemon-sword-\u0026-shield/torkoal-v-24","picture":"https://storage.googleapis.com/images.pricecharting.com/103ae1353eebbbce8ba1b11e159aab16a2f2a03e72274ebb41d733d2e17db530/240.jpg","id":19281},{"name":"Team Yell Grunt #210","price":5.68,"url":"https://www.pricecharting.com/game/pokemon-sword-\u0026-shield/team-yell-grunt-210","picture":"https://storage.googleapis.com/images.pricecharting.com/b957d922676a9b1d60832fa8a3d2c058d06fb0c7ad09862df098e9329dd3b48b/240.jpg","id":19291},{"name":"Sableye V #194","price":4.9,"url":"https://www.pricecharting.com/game/pokemon-sword-\u0026-shield/sableye-v-194","picture":"https://storage.googleapis.com/images.pricecharting.com/7dbf30572b58b48f310e98006d13c7745366202393b85f331dfe845b1ce58f73/240.jpg","id":19292},{"name":"Stonjourner V #115","price":1.82,"url":"https://www.pricecharting.com/game/pokemon-sword-\u0026-shield/stonjourner-v-115","picture":"https://storage.googleapis.com/images.pricecharting.com/e2158451df0ff8d47b357980d0d5fc8f48110cfdca7d85954f2d2fbd699f09ba/240.jpg","id":19293},{"name":"Bede #199","price":4.67,"url":"https://www.pricecharting.com/game/pokemon-sword-\u0026-shield/bede-199","picture":"https://storage.googleapis.com/images.pricecharting.com/3fe4abb74c317f4fc8422fd6c8317e6b181565340ef0053fdc263586b175c917/240.jpg","id":19294}]